mpy_cross_multi/__init__.py
mpy_cross_multi/__main__.py
mpy_cross_multi/py.typed
mpy_cross_multi-2.0.0.dist-info/METADATA
mpy_cross_multi-2.0.0.dist-info/WHEEL
mpy_cross_multi-2.0.0.dist-info/entry_points.txt
mpy_cross_multi-2.0.0.dist-info/RECORD
