Metadata-Version: 2.3
Name: mpy-cross-multi
Version: 2.0.0
Summary: MicroPython cross-compiler targeting multiple runtime versions.
License: MIT
Author: David Lechner
Author-email: david@pybricks.com
Requires-Python: >=3.9
Classifier: License :: OSI Approved :: MIT License
Classifier: Programming Language :: Python :: 3
Classifier: Programming Language :: Python :: 3.9
Classifier: Programming Language :: Python :: 3.10
Classifier: Programming Language :: Python :: 3.11
Classifier: Programming Language :: Python :: 3.12
Classifier: Programming Language :: Python :: 3.13
Requires-Dist: mpy-cross-v5 (>=1.1.0)
Requires-Dist: mpy-cross-v6 (>=1.1.0)
Requires-Dist: mpy-cross-v6.1 (>=1.0.1)
Requires-Dist: mpy-cross-v6.2 (>=1.0.0)
Requires-Dist: mpy-cross-v6.3 (>=1.0.0)
Requires-Dist: semver (>=3.0.2)
Project-URL: Homepage, https://github.com/pybricks/python-mpy-cross-multi
